NuInfoSys/__init__.py
NuInfoSys/betabrite.py
NuInfoSys/betabrite_library_tests.py
NuInfoSys/betabrite_sign_io_tests.py
NuInfoSys/config.py
NuInfoSys/debug.py
NuInfoSys/framecontrolbytes.py
NuInfoSys/memory.py
NuInfoSys/repl.py
NuInfoSys-1.0.0.dist-info/METADATA
NuInfoSys-1.0.0.dist-info/WHEEL
NuInfoSys-1.0.0.dist-info/top_level.txt
NuInfoSys-1.0.0.dist-info/RECORD
