Metadata-Version: 2.1
Name: NuInfoSys
Version: 1.0.0
Summary: NuInfoSys
Home-page: https://github.com/adamhb123/NuInfoSys
Author: Adam Brewer
Author-email: adamhb321@gmail.com
License: UNKNOWN
Platform: UNKNOWN
Classifier: Programming Language :: Python :: 3
Classifier: License :: OSI Approved :: MIT License
Classifier: Operating System :: OS Independent
Requires-Python: >=3.6
